Metadata-Version: 2.4
Name: cofactor-vigil
Version: 0.2.1
Summary: Vigil CLI: Observable, collaborative, reproducible science platform
Author: Science Abundance
License: Apache-2.0
Keywords: pipeline,provenance,receipts,reproducible,science
Classifier: Development Status :: 3 - Alpha
Classifier: Intended Audience :: Science/Research
Classifier: License :: OSI Approved :: Apache Software License
Classifier: Programming Language :: Python :: 3
Classifier: Programming Language :: Python :: 3.11
Classifier: Programming Language :: Python :: 3.12
Classifier: Programming Language :: Python :: 3.13
Requires-Python: >=3.11
Requires-Dist: pyyaml>=6.0.0
Requires-Dist: rich>=14.0.0
Requires-Dist: typer>=0.19.0
Provides-Extra: dev
Requires-Dist: cryptography>=41.0.0; extra == 'dev'
Requires-Dist: mcp>=1.1.0; extra == 'dev'
Requires-Dist: mypy>=1.8.0; extra == 'dev'
Requires-Dist: polars>=0.20.0; extra == 'dev'
Requires-Dist: pytest>=8.3.0; extra == 'dev'
Requires-Dist: ruff>=0.1.0; extra == 'dev'
Provides-Extra: mcp
Requires-Dist: mcp>=1.1.0; extra == 'mcp'
Requires-Dist: polars>=0.20.0; extra == 'mcp'
Requires-Dist: pyyaml>=6.0.0; extra == 'mcp'
